{
  "common": {
    "search": "Search",
    "language": "Language",
    "yes": "Yes",
    "no": "No",
    "cancel": "Cancel",
    "loading": "Loading...",
    "submitting": "Submitting...",
    "creating": "Creating...",
    "updating": "Updating...",
    "connecting": "Connecting...",
    "connected": "Connected",
    "disconnected": "Disconnected"
  },
  "nav": {
    "home": "Home",
    "createGame": "Create Game",
    "joinGame": "Join Game",
    "login": "Login",
    "signUp": "Sign Up",
    "settings": "Settings",
    "profile": "Profile",
    "logout": "Logout"
  },
  "footer": {
    "poweredBy": "Powered by"
  },
  "home": {
    "title1": "Guess",
    "title2": "Who's Who",
    "title3": "in real-time multiplayer experience!",
    "subtitle": "Create or join a game, ask questions and find your opponents' mystery characters.",
    "createGameButton": "Create a Game",
    "joinGameButton": "Join a Game",
    "howToPlay": "How to Play"
  },
  "about": {
    "title": "About"
  },
  "auth": {
    "signedInAs": "Signed in as",
    "logOut": "Log Out",
    "login": {
      "title": "Log In",
      "emailOrUsername": "Email or Username",
      "emailOrUsernamePlaceholder": "Enter your email or username",
      "password": "Password",
      "passwordPlaceholder": "Enter your password",
      "forgotPassword": "Forgot password?",
      "loginButton": "Log In",
      "noAccount": "Don't have an account? Sign Up",
      "fillAllFields": "Please fill in all fields",
      "invalidEmail": "Please enter a valid email address",
      "loginFailed": "Login Failed"
    },
    "register": {
      "title": "Sign Up",
      "username": "Username",
      "usernamePlaceholder": "Choose a username",
      "email": "Email",
      "emailPlaceholder": "Enter your email",
      "password": "Password",
      "passwordPlaceholder": "Choose a password",
      "confirmPassword": "Confirm Password",
      "confirmPasswordPlaceholder": "Confirm your password",
      "agreeToTerms": "I agree to the Terms of Service and Privacy Policy",
      "signUpButton": "Sign Up",
      "haveAccount": "Already have an account? Log In",
      "fillAllFields": "Please fill in all required fields",
      "invalidEmail": "Please enter a valid email address",
      "passwordsNoMatch": "Passwords do not match",
      "agreeToTermsError": "Please agree to the terms and privacy policy",
      "registrationFailed": "Registration failed",
      "verificationSent": "Verification Email Sent",
      "verificationMessage": "We've sent a verification link to your email. Please check your inbox and click the link to activate your account.",
      "resendVerification": "Resend Verification Email",
      "emailResent": "Verification email resent successfully"
    },
    "forgotPassword": {
      "title": "Forgot Password",
      "description": "Enter your email address and we'll send you a link to reset your password.",
      "email": "Email",
      "emailPlaceholder": "Enter your email",
      "sendButton": "Send Reset Link",
      "backToLogin": "Back to Log In",
      "enterEmail": "Please enter your email address",
      "resetLinkSent": "Reset Link Sent",
      "resetLinkDescription": "If an account exists with this email, you will receive a password reset link shortly.",
      "sendFailed": "Failed to send reset link"
    },
    "resetPassword": {
      "title": "Reset Password",
      "newPassword": "New Password",
      "newPasswordPlaceholder": "Enter your new password",
      "confirmPassword": "Confirm Password",
      "confirmPasswordPlaceholder": "Confirm your new password",
      "resetButton": "Reset Password",
      "passwordsNoMatch": "Passwords do not match",
      "resetSuccess": "Password Reset Successfully",
      "resetSuccessMessage": "Your password has been reset. You can now log in with your new password.",
      "backToLogin": "Back to Log In",
      "resetFailed": "Failed to reset password"
    },
    "verifyEmail": {
      "verifying": "Verifying your email...",
      "success": "Email Verified Successfully",
      "successMessage": "Your email has been verified. You can now log in to your account.",
      "failed": "Verification Failed",
      "failedMessage": "The verification link is invalid or has expired.",
      "goToLogin": "Go to Log In"
    },
    "profile": {
      "title": "Profile Settings",
      "username": "Username",
      "usernamePlaceholder": "Enter your username",
      "email": "Email",
      "emailPlaceholder": "Enter your email",
      "avatarUrl": "Avatar URL",
      "avatarUrlPlaceholder": "Enter your avatar URL",
      "currentPassword": "Current Password",
      "currentPasswordPlaceholder": "Enter your current password",
      "newPassword": "New Password",
      "newPasswordPlaceholder": "Enter your new password",
      "confirmPassword": "Confirm Password",
      "confirmPasswordPlaceholder": "Confirm your new password",
      "updateProfile": "Update Profile",
      "changePassword": "Change Password",
      "updating": "Updating...",
      "changing": "Changing...",
      "updateSuccess": "Profile updated successfully",
      "passwordChangeSuccess": "Password changed successfully",
      "updateFailed": "Failed to update profile",
      "passwordChangeFailed": "Failed to change password",
      "invalidEmail": "Please enter a valid email address",
      "invalidUsername": "Username must be at least 3 characters",
      "invalidAvatarUrl": "Please enter a valid URL",
      "passwordsNoMatch": "Passwords do not match",
      "passwordTooShort": "Password must be at least 6 characters",
      "fillAllFields": "Please fill in all required fields",
      "emailVerificationRequired": "Email verification required. Check your inbox.",
      "emailVerified": "Email Verified",
      "emailNotVerified": "Email Not Verified",
      "resendVerification": "Resend Verification Email",
      "resendingVerification": "Sending...",
      "verificationEmailSent": "Verification email sent successfully",
      "verificationEmailFailed": "Failed to send verification email",
      "gameStats": "Game Statistics",
      "gamesPlayed": "Games Played",
      "gamesWon": "Games Won",
      "winRate": "Win Rate",
      "totalQuestions": "Questions Asked",
      "totalGuesses": "Guess Attempts",
      "fastestWin": "Fastest Win",
      "currentStreak": "Current Streak",
      "noStatsYet": "No statistics available yet. Play your first game!",
      "seconds": "seconds",
      "wins": "wins",
      "gameHistory": "Game History",
      "noGamesYet": "No games played yet. Play your first game!",
      "loadingGames": "Loading history...",
      "opponent": "Opponent",
      "victory": "Victory",
      "defeat": "Defeat",
      "placement": "Placement",
      "duration": "Duration",
      "questions": "Questions",
      "guesses": "Guesses",
      "minutes": "minutes",
      "minute": "minute",
      "showMore": "Show More",
      "showLess": "Show Less"
    }
  },
  "game": {
    "create": {
      "title": "Create Game",
      "characterSet": "Character Set",
      "characterSetPlaceholder": "Select a character set",
      "twoPlayerInfo": "This game is played with exactly 2 players",
      "turnTimer": "Turn Timer (seconds)",
      "turnTimerPlaceholder": "Enter turn timer in seconds (optional)",
      "createButton": "Create Game",
      "creating": "Creating...",
      "loadingCharacterSets": "Loading character sets...",
      "fillCharacterSet": "Please select a character set",
      "creationFailed": "Failed to create game",
      "noCharacterSets": "No character sets available",
      "authRequired": "Authentication Required",
      "authRequiredDescription": "To create a game, you must log in or continue as a guest.",
      "continueAsGuest": "Continue as Guest",
      "loginButton": "Log In"
    },
    "join": {
      "title": "Join a Game",
      "roomCode": "Room Code",
      "roomCodePlaceholder": "Enter 5-character room code",
      "joinButton": "Join Game",
      "backToHome": "Back to Home",
      "enterRoomCode": "Please enter a room code",
      "invalidRoomCode": "Room code must be 5 characters",
      "joinFailed": "Failed to join game",
      "joining": "Joining game...",
      "authRequired": "Authentication Required",
      "authRequiredDescription": "To join a game, you must log in or continue as a guest.",
      "continueAsGuest": "Continue as Guest",
      "loginButton": "Log In"
    },
    "lobby": {
      "title": "Game Lobby",
      "roomCode": "Room Code",
      "copyRoomCode": "Copy Code",
      "roomCodeCopied": "Room code copied!",
      "host": "Host",
      "players": "Players",
      "waitingForPlayers": "Waiting for players to join...",
      "needTwoPlayers": "2 players are required to start the game",
      "readyStatus": "Ready",
      "notReadyStatus": "Not Ready",
      "toggleReady": "Toggle Ready",
      "toggleNotReady": "Toggle Not Ready",
      "startGame": "Start Game",
      "leaveLobby": "Leave Lobby",
      "connected": "Connected",
      "disconnected": "Disconnected",
      "connecting": "Connecting...",
      "allPlayersReady": "All players are ready!",
      "notAllPlayersReady": "Both players must be ready to start the game.",
      "waitingForHost": "Waiting for host to start the game...",
      "gameStarting": "Game Starting!",
      "redirectingToGame": "Redirecting to game...",
      "errors": {
        "failedToJoin": "Failed to join lobby",
        "failedToUpdateReady": "Failed to update ready status",
        "failedToStartGame": "Failed to start game",
        "failedToCopyRoomCode": "Failed to copy room code",
        "disconnected": "You have been disconnected from the lobby",
        "roomNotFound": "Room not found"
      }
    },
    "play": {
      "title": "Game In Progress",
      "roomCode": "Room Code",
      "roomCodeCopied": "Room code copied!",
      "round": "Round",
      "turn": "Turn",
      "yourTurn": "Your Turn!",
      "playerTurn": "{player}'s Turn",
      "waitingForTurn": "Waiting for your turn...",
      "yourCharacter": "Your Character",
      "timer": "Time Remaining",
      "connecting": "Connecting to game...",
      "loadingGame": "Loading game state...",
      "eliminated": "You have been eliminated!",
      "characters": {
        "characterGrid": "Character Grid",
        "activeCharacters": "Active Characters",
        "eliminatedCharacters": "Eliminated Characters",
        "flippedCharacters": "Flipped Characters",
        "noCharactersYet": "Loading characters...",
        "noCharacterSelected": "No character selected",
        "selectCharacterFirst": "Select a character from the grid",
        "selectCharacterToGuess": "Select the character you want to guess:",
        "selectedCharacter": "Selected character:"
      },
      "questions": {
        "questionsPanel": "Ask a Question",
        "questionPlaceholder": "Type your question here...",
        "selectPlayer": "Select target player",
        "askButton": "Ask Question",
        "asking": "Asking...",
        "history": "Question History",
        "noQuestionsYet": "No questions asked yet",
        "askedBy": "Asked by",
        "to": "to",
        "answered": "Answered",
        "enterQuestion": "Please enter a question"
      },
      "answers": {
        "answerButton": "Answer",
        "answerQuestion": "Answer Question",
        "yourAnswer": "Your Answer",
        "optionalDetails": "Optional Details",
        "optionalDetailsPlaceholder": "Add any additional details...",
        "submitAnswer": "Submit Answer",
        "submitting": "Submitting...",
        "cancel": "Cancel",
        "yes": "Yes",
        "no": "No",
        "unsure": "Unsure",
        "answerSubmitted": "Answer submitted"
      },
      "guess": {
        "guessPanel": "Make a Guess",
        "guessDescription": "Select a character to guess",
        "selectCharacter": "Select a character",
        "guessButton": "Make Guess",
        "guessing": "Guessing...",
        "cancelGuess": "Cancel",
        "confirmGuess": "Confirm Your Guess",
        "confirmGuessDescription": "Are you sure you want to guess this character?",
        "confirmButton": "Confirm Guess",
        "correctGuess": "Correct guess!",
        "incorrectGuess": "Incorrect guess"
      },
      "actions": {
        "abandonGame": "Leave Game",
        "confirmAbandon": "Are you sure you want to leave the game?"
      },
      "gameOver": "Game Over",
      "errors": {
        "failedToLoad": "Failed to load game",
        "failedToAskQuestion": "Failed to ask question",
        "failedToGuess": "Failed to make guess",
        "failedToAnswer": "Failed to submit answer",
        "failedToCopyRoomCode": "Failed to copy room code",
        "notYourTurn": "It's not your turn",
        "selectCharacter": "Please select a character",
        "selectCharacterDescription": "Select a character from the grid before making a guess"
      }
    },
    "results": {
      "title": "Game Over",
      "winner": "Winner",
      "congratulations": "Congratulations!",
      "youWon": "You Won!",
      "youLost": "Better luck next time!",
      "you": "You",
      "roomCode": "Room Code",
      "roomCodeCopied": "Room code copied!",
      "loading": "Loading results...",
      "stats": {
        "gameStats": "Game Statistics",
        "playerStats": "Player Statistics",
        "detailedStats": "Your Detailed Stats",
        "duration": "Duration",
        "rounds": "Rounds",
        "placement": "Placement",
        "username": "Player",
        "score": "Score",
        "questionsAsked": "Questions Asked",
        "questionsAnswered": "Questions Answered",
        "correctGuesses": "Correct Guesses",
        "incorrectGuesses": "Incorrect Guesses",
        "totalGuesses": "Total Guesses",
        "timePlayed": "Time Played",
        "first": "1st",
        "second": "2nd",
        "third": "3rd",
        "nth": "{n}th",
        "minutes": "{n} min",
        "seconds": "{n} sec"
      },
      "actions": {
        "newGame": "New Game",
        "backToHome": "Back to Home",
        "viewCharacterSet": "View Character Set"
      },
      "errors": {
        "failedToLoad": "Failed to load game results",
        "failedToCopyRoomCode": "Failed to copy room code",
        "gameNotCompleted": "This game is not yet completed"
      }
    }
  }
}
